airtop_langgraph_helpers/__init__.py
airtop_langgraph_helpers/helpers.py
airtop_langgraph_helpers-0.1.1.dist-info/LICENSE
airtop_langgraph_helpers-0.1.1.dist-info/METADATA
airtop_langgraph_helpers-0.1.1.dist-info/WHEEL
airtop_langgraph_helpers-0.1.1.dist-info/top_level.txt
airtop_langgraph_helpers-0.1.1.dist-info/RECORD
