Metadata-Version: 2.1
Name: airtop_langgraph_helpers
Version: 0.1.1
Summary: A small package containing class definitions and helpers for integrating Airtop into your LangGraph application
Home-page: https://github.com/airtop-ai/airtop_langgraph_helpers
Author: Airtop
Classifier: Programming Language :: Python :: 3
Classifier: License :: OSI Approved :: MIT License
Classifier: Operating System :: OS Independent
Requires-Python: >=3.6
License-File: LICENSE
